{
  "@@locale": "am",
  "app": {
    "name": "ዛሬሻፕ ተጠቃሚ",
    "version": "1.0.0",
    "description": "ዛሬሻፕ ተጠቃሚ መተግበሪያ ኢትዮጵያዊ ነጋዴዎች የመስመር ላይ ንግዳቸውን በብቃት እንዲያስተዳድሩ ይረዳቸዋል።"
  },
  "paymentMethods": {
    "title": "የክፍያ ዘዴዎች",
    "setDefault": "እንደ ነባሪ የክፍያ ዘዴ አድርግ",
    "add": "የክፍያ ዘዴ ያክሉ",
    "addDesc": "ክፍያ ለመቀበል አዲስ የክፍያ ዘዴ ያክሉ።",
    "edit": "አርትዖት",
    "remove": "አስወግድ",
    "bankTransfer": "የባንክ ዝውውር",
    "mobileWallet": "የሞባይል ቦርሳ",
    "debitCreditCard": "ዴቢት/ክሬዲት ካርድ",
    "dialogTitle": "የክፍያ ዘዴ ጨምር",
    "methodLabel": "የክፍያ ዘዴ",
    "telebirr": "ተለቢርር",
    "cbeBirr": "ሲቢኢ ብር",
    "bankAccount": "የባንክ ሂሳብ",
    "accountHolderName": "የሂሳብ ባለቤት ስም",
    "accountHolderNameHint": "የሂሳብ ባለቤት ስም ያስገቡ",
    "phoneNumber": "ስልክ ቁጥር",
    "useRegistrationPhone": "የመመዝገብ ስልክ ቁጥር ተጠቀም?",
    "useRegistrationPhoneDesc": "ከመመዝገብዎ ጋር ተመሳሳይ የስልክ ቁጥር ተጠቀም",
    "bankAccountNumber": "የባንክ ሂሳብ ቁጥር",
    "bankAccountNumberHint": "የባንክ ሂሳብ ቁጥር ያስገቡ",
    "cancel": "ይቅር",
    "confirmAdd": "ጨምር",
    "addSuccess": "የክፍያ ዘዴ በተሳካ ሁኔታ ታክሏል!",
    "telebirrDesc": "የሞባይል ቦርሳ የክፍያ ስርዓት",
    "cbeBirrDesc": "የCommercial Bank of Ethiopia ሞባይል ባንክ",
    "bankTransferDesc": "ባህላዊ የባንክ ሂሳብ ዝውውር"
  },
  "help": {
    "title": "ድጋፍን ያግኙ",
    "subtitle": "እርዳታ ይፈልጋሉ? ለመርዳት እንልፋለን!",
    "sendMessage": "መልእክት ወደ አስተዳዳሪ ላክ",
    "notifyByPhone": "በስልክ ቁጥር ይጠብቁ ይደርስዎታል",
    "callUs": "ዛሬሻፕን ይደውሉ",
    "email": "የኢሜይል ድጋፍ",
    "responseSla": "በ4 ሰዓታት ውስጥ እንመልሳለን። የድጋፍ ቡድናችን ሰኞ-አርብ ከ3:00-12:00 እና ከ2:00-5:00 ድረስ ይገኛል"
  },
  "common": {
    "loading": "በመጫን ላይ...",
    "error": "ስህተት",
    "success": "ተሳክቷል",
    "cancel": "ሰርዝ",
    "close": "ዝጋ",
    "save": "አስቀምጥ",
    "continue": "ቀጥል",
    "back": "ተመለስ",
    "next": "ቀጣይ",
    "done": "ተጠናቋል",
    "retry": "እንደገና ሞክር",
    "confirm": "አረጋግጥ",
    "yes": "አዎ",
    "no": "አይ",
    "ok": "እሺ",
    "edit": "አርትዖት",
    "delete": "ሰርዝ",
    "add": "ጨምር",
    "remove": "አስወግድ",
    "search": "ፈልግ",
    "filter": "አጣራ",
    "sort": "ደርድር",
    "refresh": "አድስ",
    "submit": "ላክ",
    "reset": "እንደገና ጀምር",
    "clear": "አጽዳ",
    "select": "መርጥ",
    "choose": "መርጥ",
    "upload": "ጫን",
    "download": "አውርድ",
    "view": "እይ",
    "details": "ዝርዝሮች",
    "settings": "ቅንብሮች",
    "help": "እርዳታ",
    "about": "ስለ",
    "contact": "አግኝ",
    "support": "ድጋፍ",
    "terms": "ውሎች",
    "privacy": "ግላዊነት",
    "language": "ቋንቋ",
    "theme": "ገጽታ",
    "comingSoon": "ለቅርብ ይመጣል!"
  },
  "auth": {
    "login": {
      "title": "ግባ",
      "welcome": "እንኳን ደህና መጡ!",
      "subtitle": "ሱቅዎን ለመስተዳደር እና ንግድዎን ለማዳበር ይግቡ።",
      "phoneNumber": "ስልክ ቁጥር",
      "phoneHint": "912345678",
      "password": "የይለፍ ቃል",
      "passwordHint": "የይለፍ ቃልዎን ያስገቡ",
      "forgotPassword": "የይለፍ ቃል ረሳሁ?",
      "loginButton": "ግባ",
      "noAccount": "መለያ የለዎትም?",
      "signUp": "ተመዝግብ",
      "fillFields": "እባክዎ ሁሉንም መስኮች በትክክል ይሙሉ",
      "invalidCredentials": "ስልክ ቁጥር ወይም የይለፍ ቃል ትክክል አይደለም",
      "loginSuccess": "መግባት ተሳክቷል!",
      "loginError": "መግባት አልተሳካም። እባክዎ እንደገና ይሞክሩ።"
      ,
      "secureLogin": "ደህንነቱ የተጠበቀ መግቢያ"
    },
    "forgotPassword": {
      "title": "የይለፍ ቃል እንደገና አስቀምጥ",
      "subtitle": "የይለፍ ቃል እንደገና ለማስቀመጥ የስልክ ቁጥርዎን ያስገቡ",
      "description": "የይለፍ ቃልዎን ረሳሁ?",
      "descriptionText": "አትጨነቅ! የስልክ ቁጥርዎን ያስገቡ እና የይለፍ ቃልዎን እንደገና ለማስቀመጥ የማረጋገጫ ኮድ እንልክላችሁ።",
      "phoneNumber": "ስልክ ቁጥር",
      "phoneHint": "912345678",
      "sendCode": "የማረጋገጫ ኮድ ላክ",
      "phoneError": "ስልክ ቁጥር 9 አሃዞች መሆን አለበት",
      "phoneErrorStart": "ስልክ ቁጥር በ9 መጀመር አለበት",
      "otpSent": "OTP ወደ {phoneNumber} ተልኳል",
      "invalidPhone": "እባክዎ ትክክለኛ የስልክ ቁጥር ያስገቡ"
    },
    "verifyOtp": {
      "title": "OTP አረጋግጥ",
      "subtitle": "ወደ {phoneNumber} የተላከውን ኮድ ያስገቡ",
      "description": "የማረጋገጫ ኮድ ያስገቡ",
      "descriptionText": "ወደ የስልክ ቁጥርዎ 6-አሃዝ የማረጋገጫ ኮድ ልከናል። የይለፍ ቃልዎን እንደገና ለማስቀመጥ ከዚህ በታች ያስገቡ።",
      "verificationCode": "የማረጋገጫ ኮድ",
      "newPassword": "አዲስ የይለፍ ቃል",
      "newPasswordHint": "አዲስ የይለፍ ቃል ያስገቡ",
      "confirmPassword": "የይለፍ ቃል አረጋግጥ",
      "confirmPasswordHint": "አዲስ የይለፍ ቃል አረጋግጥ",
      "resetPassword": "የይለፍ ቃል እንደገና አስቀምጥ",
      "resendCode": "ኮድ እንደገና ላክ",
      "passwordError": "የይለፍ ቃል ቢያንስ 6 ቁምፊዎች መሆን አለበት",
      "passwordMismatch": "የይለፍ ቃሎች አይዛመዱም",
      "fillFields": "እባክዎ ሁሉንም መስኮች በትክክል ይሙሉ",
      "resetSuccess": "የይለፍ ቃል እንደገና ማስቀመጥ ተሳክቷል!"
    }
  },
  "onboarding": {
    "progress": {
      "stepOf": "እርምጃ {current} ከ {total}",
      "step": "እርምጃ",
      "finishSetup": "ማቀናበር አጠናቀቅ"
    },
    "welcome": {
      "title": "ወደ ዛሬሻፕ ተጠቃሚ እንኳን ደህና መጡ!",
      "subtitle": "ሱቅዎን በጥቂት ቀላል ደረጃዎች እናስቀምጥ።",
      "description": "የንግድ መገለጫዎን ይበጃጃሉ፣ የመጀመሪያ ምርቶችዎን ይጨምራሉ፣ እና የክፍያ አማራጮችን ያገናኙ።",
      "vendorPortal": "ተጠቃሚ ፖርታል"
    },
    "phoneNumber": {
      "title": "ስልክ ቁጥር",
      "subtitle": "ለመጀመር የስልክ ቁጥርዎን ያስገቡ",
      "phoneHint": "912345678",
      "continue": "ቀጥል",
      "phoneError": "እባክዎ ትክክለኛ የስልክ ቁጥር ያስገቡ",
      "infoText": "ለማረጋገጥ 6-አሃዝ ያለ ኦቲፒ እንልካለን።",
      "passwordLabel": "የይለፍ ቃል",
      "passwordHint": "የይለፍ ቃልዎን ያስገቡ"
    },
    "basicInfo": {
      "title": "መሰረታዊ መረጃ",
      "subtitle": "ስለ ንግድዎ ይንገሩን",
      "businessName": "የንግድ ስም",
      "nameHint": "የንግድ ስምዎን ያስገቡ",
      "businessDescription": "የንግድ መግለጫ",
      "descriptionHint": "ስለ ንግድዎ፣ ምርቶች እና አገልግሎቶች ይግለጹ...",
      "helperDescription": "ጥሩ መግለጫ የሚሸጡትን እቃዎች እና አገልግሎቶች ለደንበኞች እንዲገባ ይረዳል።"
    },
    "documents": {
      "kycTitle": "KYC ማረጋገጫ",
      "kycSubtitle": "ለ እናንተን ደንበኞች ማወቅ (KYC) ማረጋገጫ የሚፈለጉ ሰነዶችን ይጫኑ።",
      "businessLicense": "የንግድ ፈቃድ",
      "businessLicenseRequired": "የንግድ ፈቃድ *",
      "businessLicenseDesc": "ለ KYC ማረጋገጫ የመመዝገብ ወይም የፈቃድ ሰነድዎን ይጫኑ",
      "coverImage": "የንግድ ሽፋን ምስል",
      "coverImageRequired": "የንግድ ሽፋን ምስል *",
      "coverImageDesc": "ለ KYC ማረጋገጫ ንግድዎን የሚወክል ሽፋን ምስል ይጫኑ",
      "tapToUpload": "ለመጫን ይንኩ",
      "selectFromGallery": "ከማኅተም ይምረጡ",
      "guidelinesTitle": "የ KYC ሰነድ መመሪያዎች",
      "guidelinesBullets": "• ምስሎች ግልጽ እና ንባብ የሚችሉ መሆን አለባቸው\n• የሚቀበሉ አቀራረቦች: JPG, PNG\n• ከፊደል መጠን: 5MB እስከ እያንዳንዱ ምስል\n• ሰነዶች ንብረት እና ያልተሻለ መሆን አለባቸው",
      "uploaded": "{name} ተጭኗል!"
    },
    "shippingAddress": {
      "title": "የማጓጓዣ አድራሻ",
      "subtitle": "ትዕዛዞች የት እንዲደርሱ?",
      "city": "ከተማ",
      "subcity": "ንዑስ ከተማ",
      "woreda": "ወረዳ",
      "region": "ክልል",
      "location": "አቋም",
      "tapToSelectOnMap": "በካርታ ላይ ለመምረጥ ይንኩ",
      "pickLocation": "አቋም ምረጥ",
      "addressDetails": "የአድራሻ ዝርዝር",
      "cityHint": "ለምሳሌ፣ አዲስ አበባ",
      "subcityHint": "ለምሳሌ፣ ቦሌ",
      "woredaHint": "ለምሳሌ፣ 01",
      "regionHint": "ለምሳሌ፣ አዲስ አበባ"
    },
    "subscription": {
      "choosePlanTitle": "እቅድዎን ይምረጡ",
      "choosePlanSubtitle": "ለመጀመር የደንበኝነት እቅድ ይምረጡ",
      "loading": "የደንበኝነት እቅዶች በመጫን ላይ...",
      "loadFailed": "የደንበኝነት እቅዶችን መጫን አልተሳካም",
      "checkInternet": "እባክዎ የኢንተርኔት ግንኙነትዎን ያረጋግጡ እና እንደገና ይሞክሩ",
      "unknownPlan": "ያልታወቀ እቅድ",
      "selected": "ተመርጧል",
      "select": "ምረጥ",
      "currencyETB": "ብር",
      "perDuration": "/ {duration}",
      "features": "ባህሪያት:",
      "benefitsTitle": "የደንበኝነት ጥቅሞች",
      "benefitsBullets": "• እቅድዎን በማንኛውም ጊዜ መሻሻል ወይም መቀነስ ትችላላችሁ\n• ሁሉም እቅዶች የደንበኛ ድጋፍ ያካትታሉ\n• ክፍያ በደህንነት ይተካል\n• ምንም የተሸሸገ ክፍያ የለም",
      "agreeToPrefix": "ከዚህ ጋር እስማማለሁ",
      "termsLink": "ውሎች እና ሁኔታዎች"
    },
    "payout": {
      "title": "የክፍያ መረጃ",
      "subtitle": "ክፍያዎችን እንዴት መቀበል ይፈልጋሉ?",
      "confirmDetails": "እነዚህ ዝርዝሮች ትክክል መሆናቸውን አረጋግጣለሁ",
      "authorizePayout": "ዛሬሻፕ ክፍያዎችን እንዲያከናውን እፈቅዳለሁ",
      "accountDetails": "የሂሳብ ዝርዝር",
      "paymentAgreement": "የክፍያ ውል",
      "secureTitle": "ደህንነቱ የተጠበቀ",
      "secureDesc": "የክፍያ መረጃዎ በመረጃ መሸርሸር ይጠበቃል እና በደህና ይቀመጣል። የፋይናንስ ዝርዝሮችዎን ከሶስተኛ ወገን ጋር አንካፍልም።"
    },
    "terms": {
      "title": "ውሎች እና ሁኔታዎች",
      "subscriptionTerms": "የመመዝገብ ውሎች",
      "agreeLine": "አገልግሎታችንን ሲመዘገቡ የሚከተሉትን ውሎች ትስማማሉ:",
      "section1": {
        "title": "1. የመደበኛ እቅዶች",
        "content": "• እቅድዎን በማንኛውም ጊዜ መሻሻል ወይም መቀነስ ትችላላችሁ\n• ለውጦች በሚቀጥለው የክፍያ ዑደት ላይ ይተገበራሉ\n• ለማሻሻል የተመጣጠነ ክፍያ ሊኖር ይችላል"
      },
      "section2": {
        "title": "2. የክፍያ ውሎች",
        "content": "• ሁሉም ክፍያዎች በደህንነት ይተካሉ\n• ክፍያ በመመዝገብ ቀንዎ ላይ በራስ-ሰር ይፈጠራል\n• ያልተሳካ ክፍያ አገልግሎት ማቋረጥ ሊከትል ይችላል"
      },
      "section3": {
        "title": "3. የመሰረዣ ፖሊሲ",
        "content": "• የመመዝገብ እቅድዎን በማንኛውም ጊዜ መሰረዝ ትችላላችሁ\n• የመሰረዣ ክፍያ የለም\n• መዳረሻዎ እስከ የክፍያ ዑደት መጨረሻ ድረስ ይቀጥላል"
      },
      "section4": {
        "title": "4. የአገልግሎት ሁኔታ",
        "content": "• 99.9% ጊዜ ለመኖር እንጥራለን\n• የታቀደ ጥገና በቅድሚያ ይገለጻል\n• የጊዜያዊ መቋረጥ ስለሚፈጠር ኃላፊነት አንወስድም"
      },
      "section5": {
        "title": "5. ውሂብ እና ግላዊነት",
        "content": "• ውሂብዎ በ የግላዊነት ፖሊሲታችን መሠረት ይጠበቃል\n• የግል መረጃዎን አንሸጥም\n• የንግድ መረጃዎ ባለቤትነት ይቆያል"
      },
      "footer": "የተስማማን ሳጥን ሲሞሉ ይህን ውሎች እንደተነበብክ፣ እንደተረዳክ እና እንደተስማማክ ታረጋግጣለህ።"
    },
    "success": {
      "title": "ወደ ዛሬሻፕ እንኳን ደህና መጡ!",
      "subtitle": "መለያዎ በተሳካ ሁኔታ ተፈጥሯል",
      "description": "አሁን ንግድዎን ማስተዳደር እና ምርቶችን መጨመር ይችላሉ።",
      "getStarted": "ጀምር"
    },
    "adminApproval": {
      "readyTitle": "ለማስፈር ዝግጁ",
      "reviewIntro": "መረጃዎን ይገምግሙ እና ለአስተዳዳሪ ፍቃድ መተግበሪያዎን ያስገቡ።",
      "awaitingTitle": "የአስተዳዳሪ ፍቃድ በመጠባበቅ ላይ",
      "awaitingDesc": "መተግበሪያዎ በአስተዳዳሪያችን ቡድን በ24-48 ሰአታት ውስጥ ይገመገማል። አግባብ ካገኘ ማሳወቂያ ይቀበላሉ።",
      "whatNext": "ምን ይከሰታል?",
      "timelineSubmittedTitle": "መተግበሪያ ተልኳል",
      "timelineSubmittedDesc": "የንግድ መተግበሪያዎ በተሳካ ሁኔታ ተልኳል",
      "timelineReviewTitle": "የአስተዳዳሪ ግምገማ",
      "timelineReviewDesc": "ቡድናችን ሰነዶችዎን እና የንግድ መረጃዎን ይገመገማል",
      "timelineNotifyTitle": "የፍቃድ ማሳወቂያ",
      "timelineNotifyDesc": "አግባብ ካገኘ ኢሜይል እና የመተግበሪያ ማሳወቂያ ይቀበላሉ",
      "timelineStartTitle": "መሸጥ ጀምር",
      "timelineStartDesc": "ምርቶችን መጨመር እና ሱቅዎን ማስተዳደር ጀምር",
      "submitApplication": "መተግበሪያ አስገባ"
    },
    "vendorSubmitted": {
      "title": "መተግበሪያዎ ተልኳል!",
      "reviewTitle": "የአስተዳዳሪ ግምገማ ያስፈልጋል",
      "reviewMessage": "መተግበሪያዎ አሁን በአስተዳዳሪያችን ቡድን ግምገማ ላይ ነው። ይህ ሂደት ብዙውን ጊዜ 24-48 ሰአታት ይወስዳል። ፈቃድ ካገኘ በኢሜይል ማሳወቂያ ይቀበላሉ።",
      "contactHelp": "እርዳታን ያግኙ",
      "waitForApproval": "ፍቃድ ይጠብቁ"
    },
    "userExists": {
      "title": "መለያ አስቀድሞ አለ",
      "banner": "ተጠቃሚ አስቀድሞ አለ። እባክዎ ይግቡ።",
      "loginInstead": "ይግቡ",
      "tryDifferent": "የተለየ መረጃ ይሞክሩ"
    },
    "submissionFailed": {
      "title": "ማስረከብ አልተሳካም",
      "whatNext": "ምን እንደሚያደርጉ ቀጣይ?",
      "hint": "እባክዎ መረጃዎን ያረጋግጡ እና እንደገና ይሞክሩ። ችግኙ ከቀጠለ ግን የድጋፍ ቡድናችንን ያግኙ።",
      "tryAgain": "እንደገና ሞክር",
      "contactSupport": "ድጋፍን አግኝ"
    },
    "businessNameConflict": {
      "title": "የንግድ ስም ግጭት",
      "headerTitle": "የንግድ ስም አስቀድሞ አለ",
      "headerDesc": "ያስገባኸው የንግድ ስም በሌላ ሻጭ ተወስዷል።",
      "conflictTitle": "የስም ግጭት",
      "conflictDesc": "የንግድ ስም '{originalName}' አስቀድሞ ተመዝግቧል። እባክዎ ለንግድዎ የተለየ ስም ይምረጡ።",
      "newNameLabel": "አዲስ የንግድ ስም",
      "newNameHint": "አንድ ልዩ የንግድ ስም ያስገቡ",
      "nameRequired": "የንግድ ስም ያስፈልጋል",
      "nameTooShort": "የንግድ ስም ቢያንስ 3 ቁምፊ መሆን አለበት",
      "nameHelp": "ንግድዎን የሚወክል ልዩ ስም ይምረጡ",
      "retryButton": "በአዲስ ስም አስገባ",
      "backButton": "ለማስተካከል ተመለስ"
    }
  },
  "dashboard": {
    "title": "ዳሽቦርድ",
    "welcome": "እንኳን ደህና መጡ!",
    "summary": {
      "orders": "ትዕዛዞች",
      "products": "ምርቶች",
      "sales": "ሽያጮች",
      "customers": "ደንበኞች"
    },
    "quickActions": {
      "title": "ፈጣን ተግባሮች",
      "addProduct": "ምርት ጨምር",
      "viewOrders": "ትዕዛዞችን እይ",
      "analytics": "ትንታኔ",
      "settings": "ቅንብሮች"
    },
    "recentOrders": {
      "title": "የቅርብ ጊዜ ትዕዛዞች",
      "noOrders": "የቅርብ ጊዜ ትዕዛዞች የሉም",
      "viewAll": "ሁሉንም እይ"
    }
  },
  "profile": {
    "title": "መገለጫ",
    "account": "መለያ",
    "accountInformation": "የመለያ መረጃ",
    "language": "ቋንቋ",
    "paymentMethods": "የክፍያ ዘዴዎች",
    "preferences": "ምርጫዎች",
    "notifications": "ማሳወቂያዎች",
    "privacy": "የግላዊነት ቅንብሮች",
    "support": "ድጋፍ",
    "help": "እርዳታ እና ድጋፍ",
    "about": "ስለ",
    "logout": "ውጣ",
    "selectLanguage": "ቋንቋ ይምረጡ",
    "version": "ሥሪት: {version}"
  },
  "orders": {
    "title": "ትዕዛዞች",
    "pending": "በመጠባበቅ ላይ",
    "processing": "በማስኬድ ላይ",
    "shipped": "ተላከ",
    "completed": "ተጠናቋል",
    "cancelled": "ተሰርዟል",
    "noOrders": "ትዕዛዞች አልተገኙም",
    "orderDetails": "የትዕዛዝ ዝርዝሮች",
    "customer": "ደንበኛ",
    "total": "ጠቅላላ",
    "status": "ሁኔታ",
    "date": "ቀን"
  },
  "products": {
    "title": "ምርቶች",
    "addProduct": "ምርት ጨምር",
    "editProduct": "ምርት አርትዖት",
    "productName": "የምርት ስም",
    "description": "መግለጫ",
    "price": "ዋጋ",
    "category": "ምድብ",
    "stock": "ክምችት",
    "images": "ምስሎች",
    "noProducts": "ምርቶች አልተገኙም",
    "save": "ምርት አስቀምጥ",
    "delete": "ምርት ሰርዝ"
  },
  "wallet": {
    "title": "ቦርሳ",
    "balance": "ቀሪ ሂሳብ",
    "transactions": "ግብይቶች",
    "withdraw": "አውጣ",
    "deposit": "ያስገባ",
    "noTransactions": "ግብይቶች አልተገኙም"
  },
  "settings": {
    "title": "ቅንብሮች",
    "general": "አጠቃላይ",
    "notifications": "ማሳወቂያዎች",
    "privacy": "ግላዊነት",
    "security": "ደህንነት",
    "about": "ስለ"
  },
  "errors": {
    "networkError": "የኔትዎርክ ስህተት። እባክዎ ግንኙነትዎን ያረጋግጡ።",
    "serverError": "የሰርቨር ስህተት። እባክዎ ቆይተው እንደገና ይሞክሩ።",
    "unknownError": "ያልታወቀ ስህተት ተከስቷል።",
    "validationError": "እባክዎ ግቤትዎን ያረጋግጡ እና እንደገና ይሞክሩ።",
    "authError": "ማረጋገጫ አልተሳካም። እባክዎ እንደገና ይግቡ።",
    "permissionError": "ፈቃድ ተከልክሏል።",
    "fileError": "የፋይል መጫን አልተሳካም።",
    "timeoutError": "የጥያቄ ጊዜ አልቋል። እባክዎ እንደገና ይሞክሩ።",
    "userExists": "ተጠቃሚ አስቀድሞ አለ። እባክዎ ይግቡ.",
    "invalidOtp": "የማረጋገጫ ኮድ ትክክል አይደለም.",
    "otpExpired": "የማረጋገጫ ኮድ ጊዜው አልፎበታል። እባክዎ አዲስ ኮድ ይጠይቁ።",
    "invalidCredentials": "የስልክ ቁጥር ወይም የይለፍ ቃል ትክክል አይደለም.",
    "phoneInUse": "ይህ የስልክ ቁጥር አስቀድሞ ተጠቀምቷል.",
    "userNotFound": "ተጠቃሚ በዚህ የስልክ ቁጥር አልተገኘም።",
    "registrationFailed": "መመዝገብ አልተሳካም። እባክዎ እንደገና ይሞክሩ።",
    "vendorCreationFailed": "የንግድ ሻች መፍጠር አልተሳካም።",
    "loginAfterOtpFailed": "OTP ከተረጋገጠ በኋላ መግባት አልተሳካም።"
  },
  "validation": {
    "required": "ይህ መስኮች ያስፈልጋል",
    "email": "እባክዎ ትክክለኛ ኢሜይል አድራሻ ያስገቡ",
    "phone": "እባክዎ ትክክለኛ የስልክ ቁጥር ያስገቡ",
    "phone9Digits": "ስልክ ቁጥር 9 አሃዞች መሆን አለበት",
    "password": "የይለፍ ቃል ቢያንስ 6 ቁምፊዎች መሆን አለበት",
    "confirmPassword": "የይለፍ ቃሎች አይዛመዱም",
    "minLength": "ቢያንስ {min} ቁምፊዎች መሆን አለበት",
    "maxLength": "ከ {max} ቁምፊዎች በላይ መሆን አይችልም",
    "numeric": "እባክዎ ትክክለኛ ቁጥር ያስገቡ",
    "positive": "እባክዎ አዎንታዊ ቁጥር ያስገቡ"
  },
  "languages": {
    "en": "English",
    "am": "አማርኛ (Amharic)",
    "om": "Afaan Oromoo",
    "ti": "ትግርኛ (Tigrigna)"
  },
  "themes": {
    "selectTheme": "ገጽታዎን ይምረጡ",
    "themeDescription": "ለንግድዎ የሚስማማ ገጽታ ይምረጡ",
    "changeTheme": "ገጽታ ቀይር"
  },
  "navigation": {
    "home": "ቤት",
    "portfolio": "ፖርትፎሊዮ",
    "feed": "መመገቢያ",
    "balance": "ሚዛን",
    "settings": "ቅንብሮች"
  },
  "splash": {
    "subtitlePortal": "የነጋዴ ፖርታልዎ",
    "tagline": "አስተዳድር • ሽያጭ • እድገት",
    "loginCta": "ወደ ሱቅዎ ይግቡ",
    "signupCta": "ዛሬ ጀምሩ ለመሸጥ",
    "chooseStyle": "የእርስዎን አቀራረብ ይምረጡ",
    "theme": {
      "coffee": "ቡና",
      "green": "አረንጓዴ",
      "basic": "መሠረታዊ"
    },
    "footer": "ነጋዴዎችን ለስኬት መበረታታት"
  }
  ,
  "otp": {
    "title": "ስልክ አረጋግጥ",
    "subtitle": "ወደ ስልክዎ የተላከውን የማረጋገጫ ኮድ ያስገቡ",
    "verificationCode": "የማረጋገጫ ኮድ",
    "resendCode": "ኮድ እንደገና ላክ",
    "resendIn": "ኮድ እንደገና ላክ በ {seconds} ሰከንድ",
    "verify": "አረጋግጥ",
    "otpError": "ትክክል ያልሆነ የማረጋገጫ ኮድ",
    "didntReceive": "ኮዱ ካልደረሰ የኤስኤስኤምስ መልዕክቶችዎን ያረጋግጡ። የእንደገና ላክ ቁልፍ ከ60 ሰከንድ በኋላ ይታያል።",
    "sentSuccess": "OTP በተሳካ ሁኔታ ተልኳል"
  }
}
